LICENSE.txt
README.md
setup.cfg
setup.py
cn_amount/__init__.py
cn_amount/cn_amount.py
cn_amount.egg-info/PKG-INFO
cn_amount.egg-info/SOURCES.txt
cn_amount.egg-info/dependency_links.txt
cn_amount.egg-info/top_level.txt