Metadata-Version: 2.1
Name: cn_amount
Version: 0.0.5
Summary: 金额转中文大写
Home-page: https://www.lijusheng.top
Author: 李聚升
Author-email: finleylee111@gmail.com
License: MIT
Keywords: CN,AMOUNT
Classifier: License :: OSI Approved :: MIT License
Classifier: Programming Language :: Python :: 3.7
License-File: LICENSE.txt
